water_reserv.v
module water_reserv (
    input clk,
    input reset,
    input [3:1] s,
    output reg fr3,
    output reg fr2,
    output reg fr1,
    output reg dfr
);
    parameter A=3'b000,B=3'b001,C=3'b011,D=3'b111;
    reg [3:1]state; reg [3:1] next; reg [3:1]prev_state;
    always@(posedge clk)
        begin
            if(reset)
                begin
                state<=A;
            prev_state<=A;
                end
            else 
                begin
                prev_state<=state;
                state<=next;
                end
        end
    always@(*)
        begin
            case(s)
                3'b000: next=A;
                3'b001: next=B;
                3'b011: next=C;
                3'b111: next=D;
                default: next=A;
            endcase
        end
                
    always@(*)
        begin
           case(state)
                A: begin fr1=1; fr2=1; fr3=1; dfr=1; end
               B: begin fr1=1; fr2=1; fr3=0; 
                   if(prev_state==3'b000)
                       dfr=0; 
               else
                   dfr=1;
               end
                   //(prev_state==3'b000)?0:1; end
               C: begin fr1=1; fr2=0; fr3=0; 
                   if (prev_state==3'b111)
                       dfr= 1; 
               else
                   dfr=0;
               end
                   //(prev_state==3'b111)?1:0; end
                D: begin fr1=0; fr2=0; fr3=0; dfr=0; end
                default: begin fr1=1; fr2=1; fr3=1; dfr=1; end
            endcase
        end
            
endmodule

water_reservtb.v
`timescale 1ns/1ps

module water_reservtb;

    reg clk = 0;
    reg reset;
    reg [2:0] s;
    wire fr3, fr2, fr1, dfr;

   
    water_reserv dut (
        .clk(clk),
        .reset(reset),
        .s(s),
        .fr3(fr3),
        .fr2(fr2),
        .fr1(fr1),
        .dfr(dfr)
    );

    
    always #5 clk = ~clk;

    
    initial begin
        $dumpfile("water.vcd");      
        $dumpvars(0, water_reservtb);

        $display("Time | s   | fr1 fr2 fr3 dfr");

       
        reset = 1; s = 3'b000;
        #10;

        reset = 0;

        s = 3'b000; #10;
        $display("%4t | %b |  %b   %b   %b   %b", $time, s, fr1, fr2, fr3, dfr);

        s = 3'b001; #10;
        $display("%4t | %b |  %b   %b   %b   %b", $time, s, fr1, fr2, fr3, dfr);

        s = 3'b011; #10;
        $display("%4t | %b |  %b   %b   %b   %b", $time, s, fr1, fr2, fr3, dfr);

        s = 3'b111; #10;
        $display("%4t | %b |  %b   %b   %b   %b", $time, s, fr1, fr2, fr3, dfr);

        s = 3'b011; #10;
        $display("%4t | %b |  %b   %b   %b   %b", $time, s, fr1, fr2, fr3, dfr);

        s = 3'b000; #10;
        $display("%4t | %b |  %b   %b   %b   %b", $time, s, fr1, fr2, fr3, dfr);

        $finish;
    end

endmodule

water.vcd
$date
	Wed Jul 02 12:57:45 2025
$end
$version
	Icarus Verilog
$end
$timescale
	1ps
$end
$scope module water_reservtb $end
$var wire 1 ! fr3 $end
$var wire 1 " fr2 $end
$var wire 1 # fr1 $end
$var wire 1 $ dfr $end
$var reg 1 % clk $end
$var reg 1 & reset $end
$var reg 3 ' s [2:0] $end
$scope module dut $end
$var wire 1 % clk $end
$var wire 1 & reset $end
$var wire 3 ( s [3:1] $end
$var parameter 3 ) A $end
$var parameter 3 * B $end
$var parameter 3 + C $end
$var parameter 3 , D $end
$var reg 1 $ dfr $end
$var reg 1 # fr1 $end
$var reg 1 " fr2 $end
$var reg 1 ! fr3 $end
$var reg 3 - next [3:1] $end
$var reg 3 . prev_state [3:1] $end
$var reg 3 / state [3:1] $end
$upscope $end
$upscope $end
$enddefinitions $end
$comment Show the parameter values. $end
$dumpall
b111 ,
b11 +
b1 *
b0 )
$end
#0
$dumpvars
bx /
bx .
b0 -
b0 (
b0 '
1&
0%
x$
x#
x"
x!
$end
#5000
1$
1!
1"
1#
b0 .
b0 /
1%
#10000
0%
0&
#15000
1%
#20000
b1 -
0%
b1 '
b1 (
#25000
0$
0!
b1 /
1%
#30000
b11 -
0%
b11 '
b11 (
#35000
0"
b11 /
b1 .
1%
#40000
b111 -
0%
b111 '
b111 (
#45000
0#
b111 /
b11 .
1%
#50000
b11 -
0%
b11 '
b11 (
#55000
1$
1#
b11 /
b111 .
1%
#60000
b0 -
0%
b0 '
b0 (
#65000
1!
1"
b0 /
b11 .
1%
